trest/__init__.py
trest/curl_converter.py
trest/object_converter.py
trest/rest_request.py
trest/rest_response.py
trest/configuration/__init__.py
trest/configuration/config.py
trest/utils/__init__.py
trest/utils/logging_utils.py
trest-1.4.1.dist-info/LICENSE.md
trest-1.4.1.dist-info/METADATA
trest-1.4.1.dist-info/WHEEL
trest-1.4.1.dist-info/top_level.txt
trest-1.4.1.dist-info/RECORD
