Metadata-Version: 2.1
Name: trest
Version: 1.4.1
Summary: Basic REST client with extended logging
Author-email: l0kifs <l0kifs91@gmail.com>
License: Apache License
Project-URL: Homepage, https://github.com/l0kifs/trest_client
Keywords: rest,client,allure,logging
Classifier: License :: OSI Approved :: Apache Software License
Classifier: Programming Language :: Python
Classifier: Programming Language :: Python :: 3
Requires-Python: >=3.9
License-File: LICENSE.md
Requires-Dist: allure-pytest
Requires-Dist: requests
Requires-Dist: jto ==1.2.0
Provides-Extra: dev
Requires-Dist: pip-tools ; extra == 'dev'
Requires-Dist: pytest ; extra == 'dev'
